py-anki/__init__.py
py-anki/py-anki.py
py_anki/__init__.py
py_anki/py_anki.py
py_anki/py_anki_class.py
py_anki-0.0.6.dist-info/LICENSE.txt
py_anki-0.0.6.dist-info/METADATA
py_anki-0.0.6.dist-info/WHEEL
py_anki-0.0.6.dist-info/top_level.txt
py_anki-0.0.6.dist-info/RECORD
