Metadata-Version: 2.1
Name: py-anki
Version: 0.0.6
Summary: A simple API for Anki Spaced Repetition
Home-page: https://github.com/arman-bhaai/py-anki
Author: Abu Bakar Siddique Arman
Author-email: arman.bhaai@gmail.com
License: Custom License
Download-URL: https://pypi.org/project/py-anki/#files
Keywords: py-anki,py anki,python,ankiconnect,python anki,anki api,arman_bhaai,arman-bhaai,Abu Bakar Siddique Arman
Platform: UNKNOWN
Classifier: Development Status :: 3 - Alpha
Classifier: Intended Audience :: Education
Classifier: Programming Language :: Python :: 3
Classifier: Operating System :: MacOS :: MacOS X
Classifier: Operating System :: Microsoft :: Windows
Requires-Dist: requests
